opmcli_tool.py
opmcli/__init__.py
opmcli/attributes.py
opmcli/helper.py
opmcli/index.py
opmcli/node.py
opmcli/opensearch_api.py
opmcli/opmcli.py
opmcli-1.0.0.dist-info/LICENSE
opmcli-1.0.0.dist-info/METADATA
opmcli-1.0.0.dist-info/WHEEL
opmcli-1.0.0.dist-info/entry_points.txt
opmcli-1.0.0.dist-info/top_level.txt
opmcli-1.0.0.dist-info/RECORD
